matrix_client/__init__.py
matrix_client/api.py
matrix_client/checks.py
matrix_client/client.py
matrix_client/errors.py
matrix_client/room.py
matrix_client/user.py
matrix_client/crypto/__init__.py
matrix_client/crypto/olm_device.py
matrix_client/crypto/one_time_keys.py
test/__init__.py
test/api_test.py
test/client_test.py
test/response_examples.py
test/user_test.py
matrix_client-0.4.0.dist-info/LICENSE
matrix_client-0.4.0.dist-info/METADATA
matrix_client-0.4.0.dist-info/WHEEL
matrix_client-0.4.0.dist-info/top_level.txt
matrix_client-0.4.0.dist-info/RECORD
