Metadata-Version: 2.1
Name: matrix-client
Version: 0.4.0
Summary: Client-Server SDK for Matrix
Home-page: https://github.com/matrix-org/matrix-python-sdk
Author: The Matrix.org Team
Author-email: team@matrix.org
License: Apache License, Version 2.0
Keywords: chat sdk matrix matrix.org
Platform: UNKNOWN
Classifier: Development Status :: 3 - Alpha
Classifier: Intended Audience :: Developers
Classifier: License :: OSI Approved :: Apache Software License
Classifier: Programming Language :: Python :: 2
Classifier: Programming Language :: Python :: 3
Classifier: Topic :: Communications :: Chat
Classifier: Topic :: Communications :: Conferencing
Provides-Extra: test
Provides-Extra: doc
Provides-Extra: e2e
License-File: LICENSE
